[
  {
    "title": "Receipt-less",
    "tools": "AngularJS, MongoDB, Docker, Go",
    "image": "projects/receipt-less.png",
    "link": "https://github.com/joeySchentrup/receipt-less",
    "showImage": true,
    "showData": false
  },
  {
    "title": "Health Tracker",
    "tools": "MEAN.JS",
    "image": "projects/health-tracker.png",
    "link": "https://github.com/Group7A/health-tracker",
    "showImage": true,
    "showData": false
  },
  {
    "title": "MoneyManage.io",
    "tools": "Aurelia",
    "image": "projects/money-manage.png",
    "link": "https://github.com/jmcacioppo/MoneyManage.io",
    "showImage": true,
    "showData": false
  },
  {
    "title": "Ask Madden Stuff",
    "tools": "jQuery",
    "image": "projects/askmaddenstuff.png",
    "link": "https://github.com/jmcacioppo/askmaddenstuff",
    "showImage": true,
    "showData": false
  },
  {
    "title": "Dandelion",
    "tools": "jQuery",
    "image": "projects/dandelion.png",
    "link": "https://github.com/jmcacioppo/petaltothemetal",
    "showImage": true,
    "showData": false
  },
  {
    "title": "Pic-A-Pun",
    "tools": "Javascript, Python",
    "image": "projects/pic-a-pun.png",
    "link": "https://github.com/jmcacioppo/PicAPun.github.io",
    "showImage": true,
    "showData": false
  }
]
